<!--
SPDX-FileCopyrightText: 2025 Tay <td12233a@gmail.com>
SPDX-FileCopyrightText: 2025 slarticodefast <161409025+slarticodefast@users.noreply.github.com>
SPDX-FileCopyrightText: 2025 taydeo <td12233a@gmail.com>

SPDX-License-Identifier: MIT
-->

<Document>
  # Monitoreo y Control de Dispositivos
  Dada la naturaleza de red a nivel estación del sistema de atmosféricos, es importante contar con una forma de monitorear y controlar los dispositivos desde una ubicación central.

  Con estos sistemas, el personal de Atmosféricos puede monitorear y controlar la atmósfera en toda la estación.

  <Box>
    <GuideEntityEmbed Entity="AirAlarm" Caption=""/>
    <GuideEntityEmbed Entity="AirSensor" Caption=""/>
  </Box>
  <Box>
    ## Alarmas de Aire
  </Box>
  <Box>
    [color=#999999][italic]Monitoreo y control de dispositivos atmosféricos en un área amplia[italic][/color]
  </Box>

  <Box>
    <GuideEntityEmbed Entity="ComputerAlert" Caption=""/>
  </Box>
  <Box>
    ## Computadora de Alertas Atmosféricas
  </Box>
  <Box>
    [color=#999999][italic]Monitoreo de alarmas de aire a nivel estación[italic][/color]
  </Box>

  <Box>
    <GuideEntityEmbed Entity="ComputerAtmosMonitoring" Caption=""/>
    <GuideEntityEmbed Entity="GasPipeSensor" Caption=""/>
  </Box>
  <Box>
    ## Monitor de Red Atmosférica
  </Box>
  <Box>
    [color=#999999][italic]Monitoreo de redes de tuberías completas[italic][/color]
  </Box>

</Document>
